LICENSE
MANIFEST.in
README.rst
setup.py
django_login/__init__.py
django_login/admin.py
django_login/cms_apps.py
django_login/forms.py
django_login/models.py
django_login/tests.py
django_login/urls.py
django_login/views.py
django_login.egg-info/PKG-INFO
django_login.egg-info/SOURCES.txt
django_login.egg-info/dependency_links.txt
django_login.egg-info/top_level.txt
django_login/migrations/__init__.py
django_login/static/js/login.js
django_login/templates/django_login/home.html
django_login/templates/django_login/register.html
django_login/templates/registration/logged_out.html
django_login/templates/registration/login.html